{
  "name": "sf-boat.jpg",
  "bucket": "pwagram-practice.appspot.com",
  "metageneration": 1,
  "generation": 1693084100954,
  "contentType": "image/jpeg",
  "storageClass": "STANDARD",
  "contentDisposition": "inline",
  "downloadTokens": [
    "0aacd8e0-976c-4c87-af2e-f570580f06fb"
  ],
  "etag": "jnQ5AfpURoivpzHY0LTg7+f0zww",
  "customMetadata": {},
  "timeCreated": "2023-08-26T21:08:20.955Z",
  "updated": "2023-08-26T21:08:20.955Z",
  "size": 95743,
  "md5Hash": "DygtZLD7MG2vEgUOgS1qGQ==",
  "crc32c": "1521996264"
}